Workbook

Sheet Propriétaire
A1: INFORMATIONS PROPRIÉTAIRE
A3: Nom / Raison sociale
A4: Adresse
A5: Code postal
A6: Ville
A7: Téléphone
A8: Email
A9: SIRET
A10: N° TVA Intracommunautaire

Sheet Biens
A1: LISTE DES BIENS
A2: ID Bien | B2: Désignation | C2: Type | D2: Adresse | E2: Code postal | F2: Ville | G2: Surface (m²) | H2: Étage / Niveau | I2: Observations
A3: B001 | B3: Box A1 | C3: Stockage | D3: 12 rue des Entrepôts | E3: 75012 | F3: Paris | G3: 15 | H3: RDC
A4: B002 | B4: Box A2 | C4: Garage | D4: 12 rue des Entrepôts | E4: 75012 | F4: Paris | G4: 20 | H4: RDC
A5: B003 | B5: Box B1 | C5: Habitation | D5: 5 avenue de la République | E5: 75011 | F5: Paris | G5: 45 | H5: 2ème | I5: T2

Sheet Locataires
A1: LISTE DES LOCATAIRES
A2: ID Locataire | B2: Civilité | C2: Nom | D2: Prénom | E2: Adresse | F2: Code postal | G2: Ville | H2: Téléphone | I2: Email | J2: Observations
A3: L001 | B3: M. | C3: Dupont | D3: Jean | E3: 15 rue de la Paix | F3: 75002 | G3: Paris | H3: 06 12 34 56 78 | I3: jean.dupont@email.fr
A4: L002 | B4: Mme | C4: Martin | D4: Sophie | E4: 8 bd Voltaire | F4: 75011 | G4: Paris | H4: 06 98 76 54 32 | I4: s.martin@email.fr
A5: L003 | B5: M. | C5: Bernard | D5: Pierre | E5: 22 rue Oberkampf | F5: 75011 | G5: Paris | H5: 06 55 44 33 22 | I5: p.bernard@email.fr

Sheet Baux
A1: GESTION DES BAUX
A2: ID Bail | B2: ID Bien | C2: Désignation Bien | D2: ID Locataire | E2: Nom Locataire | F2: Date début | G2: Date fin | H2: Loyer HC (€) | I2: Charges (€) | J2: Total TTC (€) | K2: Jour d'échéance | L2: Dépôt de garantie (€) | M2: Statut | N2: Observations
A3: BAIL-001 | B3: B001 | C3: Box A1 | D3: L001 | E3: Dupont Jean | F3: 45292 | G3: 46387 | H3: 150 | I3: 20 | J3: =H3+I3 -> 170 | K3: 1 | L3: 150 | M3: Actif
A4: BAIL-002 | B4: B002 | C4: Box A2 | D4: L002 | E4: Martin Sophie | F4: 45444 | G4: 46538 | H4: 200 | I4: 30 | J4: =H4+I4 -> 230 | K4: 1 | L4: 200 | M4: Actif
A5: BAIL-003 | B5: B003 | C5: Box B1 | D5: L003 | E5: Bernard Pierre | F5: 45658 | G5: 46752 | H5: 750 | I5: 80 | J5: =H5+I5 -> 830 | K5: 1 | L5: 750 | M5: Actif | N5: T2 meublé

Sheet Suivi Paiements
A1: SUIVI DES PAIEMENTS
A2: ID Paiement | B2: ID Bail | C2: Locataire | D2: Bien | E2: Période | F2: Loyer HC (€) | G2: Charges (€) | H2: Total dû (€) | I2: Montant payé (€) | J2: Date paiement | K2: Mode paiement | L2: Solde (€) | M2: Statut | N2: N° Quittance | O2: Observations
A3: P001 | B3: BAIL-001 | C3: Dupont Jean | D3: Box A1 | E3: Janvier 2026 | F3: 150 | G3: 20 | H3: =F3+G3 -> 170 | I3: 170 | J3: 46025 | K3: Virement | L3: =H3-I3 -> 0 | M3: =IF(L3=0,"Payé",IF(I3>0,"Partiel","Impayé")) -> Payé | N3: Q-2026-001
A4: P002 | B4: BAIL-002 | C4: Martin Sophie | D4: Box A2 | E4: Janvier 2026 | F4: 200 | G4: 30 | H4: =F4+G4 -> 230 | I4: 230 | J4: 46027 | K4: Chèque | L4: =H4-I4 -> 0 | M4: =IF(L4=0,"Payé",IF(I4>0,"Partiel","Impayé")) -> Payé | N4: Q-2026-002
A5: P003 | B5: BAIL-003 | C5: Bernard Pierre | D5: Box B1 | E5: Janvier 2026 | F5: 750 | G5: 80 | H5: =F5+G5 -> 830 | I5: 830 | J5: 46024 | K5: Prélèvement | L5: =H5-I5 -> 0 | M5: =IF(L5=0,"Payé",IF(I5>0,"Partiel","Impayé")) -> Payé | N5: Q-2026-003
A6: P004 | B6: BAIL-001 | C6: Dupont Jean | D6: Box A1 | E6: Février 2026 | F6: 150 | G6: 20 | H6: =F6+G6 -> 170 | I6: 170 | J6: 46054 | K6: Virement | L6: =H6-I6 -> 0 | M6: =IF(L6=0,"Payé",IF(I6>0,"Partiel","Impayé")) -> Payé | N6: Q-2026-004
A7: P005 | B7: BAIL-002 | C7: Martin Sophie | D7: Box A2 | E7: Février 2026 | F7: 200 | G7: 30 | H7: =F7+G7 -> 230 | I7: 0 | L7: =H7-I7 -> 230 | M7: =IF(L7=0,"Payé",IF(I7>0,"Partiel","Impayé")) -> Impayé | O7: Impayé
A8: P006 | B8: BAIL-003 | C8: Bernard Pierre | D8: Box B1 | E8: Février 2026 | F8: 750 | G8: 80 | H8: =F8+G8 -> 830 | I8: 830 | J8: 46056 | K8: Prélèvement | L8: =H8-I8 -> 0 | M8: =IF(L8=0,"Payé",IF(I8>0,"Partiel","Impayé")) -> Payé | N8: Q-2026-005

Sheet Tableau de bord
A1: TABLEAU DE BORD
A3: Nombre de biens | B3: =COUNTA(Biens!A3:A100) -> 3
A4: Nombre de locataires | B4: =COUNTA(Locataires!A3:A100) -> 3
A5: Baux actifs | B5: =COUNTIF(Baux!M3:M100,"Actif") -> 3
A6: Revenus mensuels attendus | B6: =SUMPRODUCT((Baux!M3:M100="Actif")*(Baux!J3:J100)) -> 1230
A8: Paiements reçus (total) | B8: =SUM('Suivi Paiements'!I3:I500) -> 2230
A9: Impayés (total) | B9: =SUMPRODUCT(('Suivi Paiements'!L3:L500>0)*('Suivi Paiements'!L3:L500)) -> 230
A10: Nombre d'impayés | B10: =COUNTIF('Suivi Paiements'!M3:M500,"Impayé") -> 1
A11: Taux de recouvrement | B11: =IF(SUM('Suivi Paiements'!H3:H500)>0,SUM('Suivi Paiements'!I3:I500)/SUM('Suivi Paiements'!H3:H500),0) -> 0.90650407

Sheet Quittance
B1: Sélectionnez le bail : | D1: BAIL-001 | E1: Période : | G1: Avril 2026
B2: =MATCH(D1,Baux!A3:A100,0) -> 1 | C2: =INDEX(Baux!D3:D100,B2) -> L001 | D2: =INDEX(Baux!B3:B100,B2) -> B001 | E2: =MATCH(C2,Locataires!A3:A100,0) -> 1 | F2: =MATCH(D2,Biens!A3:A100,0) -> 1
B4: QUITTANCE DE LOYER
B5: ="Période : "&G1 -> Période : Avril 2026
B7: BAILLEUR | E7: LOCATAIRE
B8: =Propriétaire!B3 -> 0 | E8: =INDEX(Locataires!B3:B100,E2)&" "&INDEX(Locataires!D3:D100,E2)&" "&INDEX(Locataires!C3:C100,E2) -> M. Jean Dupont
B9: =Propriétaire!B4 -> 0 | E9: =INDEX(Locataires!E3:E100,E2) -> 15 rue de la Paix
B10: =Propriétaire!B5&" "&Propriétaire!B6 | E10: =INDEX(Locataires!F3:F100,E2)&" "&INDEX(Locataires!G3:G100,E2) -> 75002 Paris
B11: =IF(Propriétaire!B9<>"","SIRET : "&Propriétaire!B9,"")
B13: ="Bien loué : "&INDEX(Biens!B3:B100,F2)&" ("&INDEX(Biens!C3:C100,F2)&")" -> Bien loué : Box A1 (Stockage)
B14: ="Adresse : "&INDEX(Biens!D3:D100,F2)&" - "&INDEX(Biens!E3:E100,F2)&" "&INDEX(Biens!F3:F100,F2) -> Adresse : 12 rue des Entrepôts - 75012 Paris
B15: ="Bail n° : "&D1 -> Bail n° : BAIL-001
B17: DÉTAIL DU PAIEMENT
B19: Désignation | F19: Montant
B20: Loyer hors charges | F20: =INDEX(Baux!H3:H100,B2) -> 150
B21: Provision pour charges | F21: =INDEX(Baux!I3:I100,B2) -> 20
B23: TOTAL | F23: =F20+F21 -> 170
B25: ="Le bailleur, "&Propriétaire!B3&", propriétaire du logement désigné ci-dessus, déclare avoir reçu de "&INDEX(Locataires!B3:B100,E2)&" "&INDEX(Locataires!D3:D100,E2)&" "&INDEX(Locataires!C3:C100,E2)&" la somme de "&TEXT(F23,"#,##0.00 €")&" au titre du paiement du loyer et des charges pour la période de "&G1&"." -> Le bailleur, , propriétaire du logement désigné ci-dessus, déclare avoir reçu de M. Jean Dupont la somme de 170.00 € au titre du paiement du loyer et des charges pour la période de Avril 2026.
B26: Cette quittance annule tous les reçus qui auraient pu être délivrés pour acomptes versés au titre de cette même période.
B27: Elle est délivrée sous réserve de tous droits, actions et procédures du bailleur.
E29: ="Fait à "&Propriétaire!B6 -> Fait à
E30: ="Le "&TEXT(TODAY(),"DD/MM/YYYY") -> Le 14/04/2026
E32: Signature du bailleur :
B35: Document généré automatiquement - Gestion Locative

Sheet Avis d'échéance
B1: Sélectionnez le bail : | D1: BAIL-001 | E1: Période : | G1: Avril 2026
B2: =MATCH(D1,Baux!A3:A100,0) -> 1 | C2: =INDEX(Baux!D3:D100,B2) -> L001 | D2: =INDEX(Baux!B3:B100,B2) -> B001 | E2: =MATCH(C2,Locataires!A3:A100,0) -> 1 | F2: =MATCH(D2,Biens!A3:A100,0) -> 1
B4: AVIS D'ÉCHÉANCE
B5: ="Période : "&G1 -> Période : Avril 2026
B7: BAILLEUR | E7: LOCATAIRE
B8: =Propriétaire!B3 -> 0 | E8: =INDEX(Locataires!B3:B100,E2)&" "&INDEX(Locataires!D3:D100,E2)&" "&INDEX(Locataires!C3:C100,E2) -> M. Jean Dupont
B9: =Propriétaire!B4 -> 0 | E9: =INDEX(Locataires!E3:E100,E2) -> 15 rue de la Paix
B10: =Propriétaire!B5&" "&Propriétaire!B6 | E10: =INDEX(Locataires!F3:F100,E2)&" "&INDEX(Locataires!G3:G100,E2) -> 75002 Paris
B13: ="Bien loué : "&INDEX(Biens!B3:B100,F2)&" ("&INDEX(Biens!C3:C100,F2)&")" -> Bien loué : Box A1 (Stockage)
B14: ="Adresse : "&INDEX(Biens!D3:D100,F2)&" - "&INDEX(Biens!E3:E100,F2)&" "&INDEX(Biens!F3:F100,F2) -> Adresse : 12 rue des Entrepôts - 75012 Paris
B15: ="Bail n° : "&D1 -> Bail n° : BAIL-001
B17: ="Montant à régler : "&TEXT(INDEX(Baux!H3:H100,B2)+INDEX(Baux!I3:I100,B2),"#,##0.00 €") -> Montant à régler : 170.00 €
B19: DÉTAIL DE L'ÉCHÉANCE
B21: Désignation | F21: Montant
B22: Loyer hors charges | F22: =INDEX(Baux!H3:H100,B2) -> 150
B23: Provision pour charges | F23: =INDEX(Baux!I3:I100,B2) -> 20
B25: TOTAL À RÉGLER | F25: =F22+F23 -> 170
B27: Cet avis d'échéance ne constitue pas une quittance de loyer.
B28: La quittance vous sera délivrée après encaissement effectif du paiement.
B29: En cas de difficultés de paiement, nous vous invitons à prendre contact avec nous dans les meilleurs délais.
E31: ="Fait à "&Propriétaire!B6 -> Fait à
E32: ="Le "&TEXT(TODAY(),"DD/MM/YYYY") -> Le 14/04/2026
B35: Document généré automatiquement - Gestion Locative
